{
    "users": [
        {"id": "000", "nmec": null, "start_year": null, "end_year": null, "sex": null, "parent": null, "name": ""},
        
        {"id": "A03", "nmec": null, "start_year": 11, "end_year": null, "sex": "M", "parent": "000", "name": "Emanuel Laranjo", "image": ""},
        {"id": "A26", "nmec": null, "start_year": 11, "end_year": null, "sex": "M", "parent": "000", "name": "Guilherme Moura", "image": ""},
        
        {"id": "002", "nmec": null, "start_year": 12, "end_year": null, "sex": "M", "parent": "000", "name": "Alex Santos", "image": "https://randomuser.me/api/portraits/men/2.jpg"},
        {"id": "A01", "nmec": null, "start_year": 12, "end_year": null, "sex": "M", "parent": "000", "name": "Rafael Martins", "image": ""},
        
        {"id": "003", "nmec": null, "start_year": 13, "end_year": null, "sex": "M", "parent": "A01", "name": "Bruno Barbosa", "image": "https://randomuser.me/api/portraits/men/3.jpg"},
        {"id": "A04", "nmec": null, "start_year": 13, "end_year": null, "sex": "M", "parent": "000", "name": "David Oliveira", "image": ""},
        {"id": "A09", "nmec": null, "start_year": 13, "end_year": null, "sex": "F", "parent": "000", "name": "Mimi Cunha", "image": ""},
        {"id": "A19", "nmec": null, "start_year": 13, "end_year": null, "sex": "M", "parent": "000", "name": "Pedro Matos", "image": ""},
        {"id": "A32", "nmec": null, "start_year": 13, "end_year": null, "sex": "M", "parent": "000", "name": "David Ferreira", "image": ""},
        
        {"id": "A02", "nmec": null, "start_year": 14, "end_year": null, "sex": "M", "parent": "A01", "name": "Paulo Seixas", "image": ""},

        {"id": "004", "nmec": null, "start_year": 15, "end_year": null, "sex": "F", "parent": "003", "name": "Andreia Patrocínio", "image": "https://randomuser.me/api/portraits/women/4.jpg"},
        {"id": "005", "nmec": null, "start_year": 15, "end_year": null, "sex": "F", "parent": "003", "name": "Carolina Albuquerque", "image": "https://randomuser.me/api/portraits/women/5.jpg"},
        {"id": "006", "nmec": null, "start_year": 15, "end_year": null, "sex": "M", "parent": "002", "name": "João Artur Costa", "image": "https://randomuser.me/api/portraits/men/6.jpg"},
        {"id": "007", "nmec": null, "start_year": 15, "end_year": null, "sex": "M", "parent": "A03", "name": "João Ferreira", "image": "https://randomuser.me/api/portraits/men/7.jpg"},
        {"id": "008", "nmec": null, "start_year": 15, "end_year": null, "sex": "M", "parent": "A03", "name": "João Magalhães", "image": "https://randomuser.me/api/portraits/men/8.jpg"},
        {"id": "009", "nmec": null, "start_year": 15, "end_year": null, "sex": "M", "parent": "A03", "name": "José Moreira", "image": "https://randomuser.me/api/portraits/men/9.jpg"},
        {"id": "A05", "nmec": null, "start_year": 15, "end_year": null, "sex": "M", "parent": "A04", "name": "Daniel Gonçalves", "image": ""},
        {"id": "A06", "nmec": null, "start_year": 15, "end_year": null, "sex": "M", "parent": "003", "name": "António Castanheira", "image": ""},
        {"id": "A10", "nmec": null, "start_year": 15, "end_year": null, "sex": "M", "parent": "A09", "name": "Fred Avó", "image": ""},
        {"id": "A11", "nmec": null, "start_year": 15, "end_year": null, "sex": "M", "parent": "A09", "name": "Nuno Silva", "image": ""},
        {"id": "A15", "nmec": null, "start_year": 15, "end_year": null, "sex": "M", "parent": "002", "name": "Diogo Jorge Ferreira", "image": ""},
        {"id": "A16", "nmec": null, "start_year": 15, "end_year": null, "sex": "M", "parent": "002", "name": "João Soares", "image": ""},
        {"id": "A20", "nmec": null, "start_year": 15, "end_year": null, "sex": "M", "parent": "A19", "name": "Carlos Soares", "image": ""},
        {"id": "A27", "nmec": null, "start_year": 15, "end_year": null, "sex": "M", "parent": "A26", "name": "Tiago Cardoso", "image": ""},
        {"id": "A28", "nmec": null, "start_year": 15, "end_year": null, "sex": "M", "parent": "A26", "name": "Saveliy Ivanov", "image": ""},
        {"id": "A29", "nmec": null, "start_year": 15, "end_year": null, "sex": "M", "parent": "A26", "name": "Miguel Simões", "image": ""},
        {"id": "A33", "nmec": null, "start_year": 15, "end_year": null, "sex": "M", "parent": "A32", "name": "Daniel Lopes", "image": ""},
        {"id": "A34", "nmec": null, "start_year": 15, "end_year": null, "sex": "M", "parent": "A32", "name": "David Fernandes", "image": ""},
        {"id": "A35", "nmec": null, "start_year": 15, "end_year": null, "sex": "M", "parent": "A32", "name": "Manuel Felizardo", "image": ""},

        {"id": "010", "nmec": null, "start_year": 16, "end_year": null, "sex": "M", "parent": "000", "name": "Francisco Silveira", "image": "https://randomuser.me/api/portraits/men/10.jpg"},
        {"id": "011", "nmec": null, "start_year": 16, "end_year": null, "sex": "F", "parent": "004", "name": "Sandra Andrade" , "image": "https://randomuser.me/api/portraits/women/11.jpg"},
        {"id": "015", "nmec": null, "start_year": 16, "end_year": null, "sex": "M", "parent": "003", "name": "João Abílio Rodrigues", "image": "https://randomuser.me/api/portraits/men/15.jpg"},
        {"id": "A07", "nmec": null, "start_year": 16, "end_year": null, "sex": "M", "parent": "003", "name": "Simão Arrais", "image": ""},
        {"id": "A08", "nmec": null, "start_year": 16, "end_year": null, "sex": "F", "parent": "003", "name": "Mariana Sequeira", "image": ""},
        {"id": "A12", "nmec": null, "start_year": 16, "end_year": null, "sex": "F", "parent": "A09", "name": "Rafaela Vieira", "image": ""},
        {"id": "A13", "nmec": null, "start_year": 16, "end_year": null, "sex": "F", "parent": "A09", "name": "Carolina Marques", "image": ""},
        {"id": "A14", "nmec": null, "start_year": 16, "end_year": null, "sex": "M", "parent": "A09", "name": "Daniel Nunes", "image": ""},
        {"id": "A17", "nmec": null, "start_year": 16, "end_year": null, "sex": "M", "parent": "002", "name": "Pedro Ferreira", "image": ""},
        {"id": "A18", "nmec": null, "start_year": 16, "end_year": null, "sex": "M", "parent": "002", "name": "Filipe Pires", "image": ""},
        {"id": "A21", "nmec": null, "start_year": 16, "end_year": null, "sex": "F", "parent": "A19", "name": "Catarina Xavier", "image": ""},
        {"id": "A22", "nmec": null, "start_year": 16, "end_year": null, "sex": "M", "parent": "A19", "name": "Pedro Fajardo", "image": ""},
        {"id": "A23", "nmec": null, "start_year": 16, "end_year": null, "sex": "M", "parent": "A19", "name": "Vitor Fajardo", "image": ""},
        {"id": "A24", "nmec": null, "start_year": 16, "end_year": null, "sex": "M", "parent": "A19", "name": "Rafael Batista", "image": ""},
        {"id": "A25", "nmec": null, "start_year": 16, "end_year": null, "sex": "M", "parent": "A19", "name": "Pedro Matos", "image": ""},
        {"id": "A30", "nmec": null, "start_year": 16, "end_year": null, "sex": "M", "parent": "A26", "name": "André Gomes", "image": ""},
        {"id": "A31", "nmec": null, "start_year": 16, "end_year": null, "sex": "M", "parent": "A26", "name": "Luís Cardoso", "image": ""},

        {"id": "012", "nmec": null, "start_year": 17, "end_year": null, "sex": "M", "parent": "005", "name": "André Alves", "image": "https://randomuser.me/api/portraits/men/12.jpg"},
        {"id": "013", "nmec": null, "start_year": 17, "end_year": null, "sex": "M", "parent": "004", "name": "André Gual", "image": "https://randomuser.me/api/portraits/men/13.jpg"},
        {"id": "014", "nmec": null, "start_year": 17, "end_year": null, "sex": "M", "parent": "005", "name": "Carina Neves", "image": "https://randomuser.me/api/portraits/men/14.jpg"},
        {"id": "016", "nmec": null, "start_year": 17, "end_year": null, "sex": "F", "parent": "004", "name": "Mariana Gameiro" , "image": "https://randomuser.me/api/portraits/women/16.jpg"},
        {"id": "017", "nmec": null, "start_year": 17, "end_year": null, "sex": "M", "parent": "004", "name": "Pedro Escaleira" , "image": "https://randomuser.me/api/portraits/men/17.jpg"},
        {"id": "018", "nmec": null, "start_year": 17, "end_year": null, "sex": "M", "parent": "000", "name": "Tiago Mendes", "image": "https://randomuser.me/api/portraits/men/18.jpg"},
        {"id": "019", "nmec": null, "start_year": 17, "end_year": null, "sex": "M", "parent": "003", "name": "Tomás Costa", "image": "https://randomuser.me/api/portraits/men/19.jpg"},

        {"id": "020", "nmec": null, "start_year": 18, "end_year": null, "sex": "M", "parent": "004", "name": "Abel Rodrigues" , "image": "https://randomuser.me/api/portraits/men/20.jpg"},
        {"id": "021", "nmec": null, "start_year": 18, "end_year": null, "sex": "M", "parent": "018", "name": "Afonso Silva", "image": "https://randomuser.me/api/portraits/men/21.jpg"},
        {"id": "022", "nmec": null, "start_year": 18, "end_year": null, "sex": "M", "parent": "007", "name": "Bruno Bastos", "image": "https://randomuser.me/api/portraits/men/22.jpg"},
        {"id": "023", "nmec": null, "start_year": 18, "end_year": null, "sex": "F", "parent": "008", "name": "Carolina Araújo", "image": "https://randomuser.me/api/portraits/women/23.jpg"},
        {"id": "024", "nmec": null, "start_year": 18, "end_year": null, "sex": "M", "parent": "015", "name": "Daniel Gomes", "image": "https://randomuser.me/api/portraits/men/24.jpg"},
        {"id": "025", "nmec": null, "start_year": 18, "end_year": null, "sex": "M", "parent": "009", "name": "Diogo Guimarães Silva", "image": "https://randomuser.me/api/portraits/men/25.jpg"},
        {"id": "026", "nmec": null, "start_year": 18, "end_year": null, "sex": "M", "parent": "014", "name": "Duarte Mortágua", "image": "https://randomuser.me/api/portraits/men/26.jpg"},
        {"id": "027", "nmec": null, "start_year": 18, "end_year": null, "sex": "M", "parent": "004", "name": "Eduardo Santos" , "image": "https://randomuser.me/api/portraits/men/27.jpg"},
        {"id": "028", "nmec": null, "start_year": 18, "end_year": null, "sex": "M", "parent": "005", "name": "Gonçalo Matos", "image": "https://randomuser.me/api/portraits/men/28.jpg"},
        {"id": "029", "nmec": null, "start_year": 18, "end_year": null, "sex": "M", "parent": "015", "name": "Hugo Paiva", "image": "https://randomuser.me/api/portraits/men/29.jpg"},
        {"id": "030", "nmec": null, "start_year": 18, "end_year": null, "sex": "M", "parent": "004", "name": "Leandro Silva" , "image": "https://randomuser.me/api/portraits/men/30.jpg"},
        {"id": "031", "nmec": null, "start_year": 18, "end_year": null, "sex": "M", "parent": "006", "name": "Luís Valentim", "image": "https://randomuser.me/api/portraits/men/31.jpg"},
        {"id": "032", "nmec": null, "start_year": 18, "end_year": null, "sex": "M", "parent": "012", "name": "Mário Silva", "image": "https://randomuser.me/api/portraits/men/32.jpg"},
        {"id": "033", "nmec": null, "start_year": 18, "end_year": null, "sex": "M", "parent": "010", "name": "Pedro Bastos", "image": "https://randomuser.me/api/portraits/men/33.jpg"},
        {"id": "034", "nmec": null, "start_year": 18, "end_year": null, "sex": "M", "parent": "005", "name": "Pedro Tavares", "image": "https://randomuser.me/api/portraits/men/34.jpg"},
        {"id": "035", "nmec": null, "start_year": 18, "end_year": null, "sex": "M", "parent": "008", "name": "Ricardo Cruz Cruz da Rokeapfwjfwefewrfe", "image": "https://randomuser.me/api/portraits/men/35.jpg"},
        {"id": "036", "nmec": null, "start_year": 18, "end_year": null, "sex": "M", "parent": "006", "name": "Rui Filipe", "image": "https://randomuser.me/api/portraits/men/36.jpg"},

        {"id": "037", "nmec": null, "start_year": 19, "end_year": null, "sex": "M", "parent": "006", "name": "Artur Romão", "image": "https://randomuser.me/api/portraits/men/37.jpg"},
        {"id": "038", "nmec": null, "start_year": 19, "end_year": null, "sex": "F", "parent": "019", "name": "Marta Fradique", "image": "https://randomuser.me/api/portraits/women/38.jpg"},
        {"id": "039", "nmec": null, "start_year": 19, "end_year": null, "sex": "M", "parent": "005", "name": "Vicente Costa", "image": "https://randomuser.me/api/portraits/men/39.jpg"},

        {"id": "082", "nmec": null, "start_year": 19, "end_year": null, "sex": "F", "parent": "000", "name": "Eva Bartolomeu", "image": ""},

        {"id": "083", "nmec": null, "start_year": 20, "end_year": null, "sex": "M", "parent": "000", "name": "Vicente Barros", "image": ""},

        {"id": "075", "nmec": null, "start_year": 20, "end_year": null, "sex": "M", "parent": "000", "name": "Guilherme Antunes", "image": "", "patrao": "sobral"},
        {"id": "076", "nmec": null, "start_year": 20, "end_year": null, "sex": "F", "parent": "083", "name": "Catarina Costa", "image": ""},
        {"id": "077", "nmec": null, "start_year": 20, "end_year": null, "sex": "M", "parent": "000", "name": "João Sousa", "image": "", "patrao": "fabio martins"},
        {"id": "Z77", "nmec": null, "start_year": 20, "end_year": null, "sex": "M", "parent": "000", "name": "João Morais", "image": "", "patrao": "paulo"},
        {"id": "078", "nmec": null, "start_year": 20, "end_year": null, "sex": "M", "parent": "082", "name": "João Matos", "image": ""},
        {"id": "079", "nmec": null, "start_year": 20, "end_year": null, "sex": "M", "parent": "000", "name": "João Almeida Matos", "image": "", "patrao": "paulo"},
        {"id": "080", "nmec": null, "start_year": 20, "end_year": null, "sex": "M", "parent": "033", "name": "Rafael Gonçalves", "image": ""},
        {"id": "081", "nmec": null, "start_year": 20, "end_year": null, "sex": "M", "parent": "000", "name": "Tiago Carvalho", "image": "", "patrao": "paulo"},
        
        {"id": "040", "nmec": null, "start_year": 21, "end_year": null, "sex": "M", "parent": "000", "name": "Alexandre Cotorobai", "image": "", "patrao": "pedro monteiro"},
        {"id": "041", "nmec": null, "start_year": 21, "end_year": null, "sex": "F", "parent": "000", "name": "Bárbara Galiza", "image": "", "patrao": "daniela dias"},
        {"id": "042", "nmec": null, "start_year": 21, "end_year": null, "sex": "M", "parent": "000", "name": "Cristiano Nicolau", "image": "", "patrao": "andre freixo"},
        {"id": "043", "nmec": null, "start_year": 21, "end_year": null, "sex": "M", "parent": "027", "name": "Daniel Madureira", "image": ""},
        {"id": "044", "nmec": null, "start_year": 21, "end_year": null, "sex": "M", "parent": "000", "name": "David Sanches", "image": "", "patrao": "black"},
        {"id": "045", "nmec": null, "start_year": 21, "end_year": null, "sex": "F", "parent": "030", "name": "Diana Miranda", "image": ""},
        {"id": "046", "nmec": null, "start_year": 21, "end_year": null, "sex": "M", "parent": "038", "name": "Diogo Falcão", "image": ""},
        {"id": "047", "nmec": null, "start_year": 21, "end_year": null, "sex": "M", "parent": "000", "name": "Diogo Almeida", "image": "", "patrao": "dani figueiredo"},
        {"id": "048", "nmec": null, "start_year": 21, "end_year": null, "sex": "M", "parent": "000", "name": "Duarte Cruz", "image": "", "patrao": "reis"},
        {"id": "049", "nmec": null, "start_year": 21, "end_year": null, "sex": "M", "parent": "038", "name": "Gabriel Teixeira", "image": ""},
        {"id": "050", "nmec": null, "start_year": 21, "end_year": null, "sex": "M", "parent": "000", "name": "Gonçalo Sousa", "image": "", "patrao": "rosa"},
        {"id": "051", "nmec": null, "start_year": 21, "end_year": null, "sex": "M", "parent": "000", "name": "Gonçalo Ferreira", "image": "", "patrao": "trigo"},
        {"id": "052", "nmec": null, "start_year": 21, "end_year": null, "sex": "M", "parent": "000", "name": "Hugo Correia", "image": "", "patrao": "filipe seabra"},
        {"id": "053", "nmec": null, "start_year": 21, "end_year": null, "sex": "F", "parent": "000", "name": "Joana Gomes", "image": "", "patrao": "gonçalo leal"},
        {"id": "054", "nmec": null, "start_year": 21, "end_year": null, "sex": "M", "parent": "036", "name": "João Luís", "image": ""},
        {"id": "055", "nmec": null, "start_year": 21, "end_year": null, "sex": "M", "parent": "000", "name": "Joaquim Rosa", "image": "", "patrao": "filipe"},
        {"id": "056", "nmec": null, "start_year": 21, "end_year": null, "sex": "M", "parent": "030", "name": "José Gameiro", "image": ""},
        {"id": "057", "nmec": null, "start_year": 21, "end_year": null, "sex": "F", "parent": "027", "name": "Liliana Ribeiro", "image": ""},
        {"id": "058", "nmec": null, "start_year": 21, "end_year": null, "sex": "F", "parent": "000", "name": "Maria Abrunhosa", "image": "", "patrao": "gonçalo leal"},
        {"id": "059", "nmec": null, "start_year": 21, "end_year": null, "sex": "F", "parent": "000", "name": "Mariana Perna", "image": "", "patrao": "reis"},
        {"id": "060", "nmec": null, "start_year": 21, "end_year": null, "sex": "F", "parent": "000", "name": "Marta Inácio", "image": "", "patrao": "rosa"},
        {"id": "061", "nmec": null, "start_year": 21, "end_year": null, "sex": "F", "parent": "000", "name": "Matilde Teixeira", "image": "", "patrao": "rosa"},
        {"id": "062", "nmec": null, "start_year": 21, "end_year": null, "sex": "M", "parent": "000", "name": "Pedro Rodrigues", "image": "", "patrao": "fahla"},
        {"id": "063", "nmec": null, "start_year": 21, "end_year": null, "sex": "M", "parent": "008", "name": "Rafael Vilaça", "image": ""},
        {"id": "064", "nmec": null, "start_year": 21, "end_year": null, "sex": "M", "parent": "027", "name": "Rafael Kauati", "image": ""},
        {"id": "065", "nmec": null, "start_year": 21, "end_year": null, "sex": "F", "parent": "000", "name": "Rafaela Dias", "image": "", "patrao": "reis"},
        {"id": "066", "nmec": null, "start_year": 21, "end_year": null, "sex": "M", "parent": "000", "name": "Rodrigo Azevedo", "image": "", "patrao": "raquel"},
        {"id": "067", "nmec": null, "start_year": 21, "end_year": null, "sex": "M", "parent": "000", "name": "Rodrigo Graça", "image": "", "patrao": "rodriguez"},
        {"id": "068", "nmec": null, "start_year": 21, "end_year": null, "sex": "M", "parent": "000", "name": "Rodrigo Aguiar", "image": "", "patrao": "luis martins"},
        {"id": "069", "nmec": null, "start_year": 21, "end_year": null, "sex": "M", "parent": "000", "name": "Tiago Gomes", "image": "", "patrao": "gonçalo leal"},
        {"id": "070", "nmec": null, "start_year": 21, "end_year": null, "sex": "M", "parent": "000", "name": "Tomás Victal", "image": "", "patrao": "fahla"},
        {"id": "071", "nmec": null, "start_year": 21, "end_year": null, "sex": "M", "parent": "000", "name": "Tomás Matos", "image": "", "patrao": "trigo"},
        {"id": "072", "nmec": null, "start_year": 21, "end_year": null, "sex": "M", "parent": "027", "name": "Vasco Vouzela", "image": ""},
        {"id": "073", "nmec": null, "start_year": 21, "end_year": null, "sex": "M", "parent": "082", "name": "Vasco Faria", "image": ""},
        {"id": "074", "nmec": null, "start_year": 21, "end_year": null, "sex": "M", "parent": "033", "name": "Vitor Santos", "image": ""}
    ],
    "organizations": [
        {"user_id": "014", "year": 21, "name": "cf", "role": "Mestre de Curso"},

        {"user_id": "030", "year": 21, "name": "nei", "role": "Vogal Seccção Académica"}
    ],
    "faina": [
        {"user_id": "014", "year": 18, "other": "Carina"},

        {"user_id": "030", "year": 19, "other": "Lionel"},
        {"user_id": "030", "year": 21, "other": "Leonardo"}
    ]
}
